caspian/__init__.py
caspian/cudalib.py
caspian/activations/Activation.py
caspian/activations/ELU.py
caspian/activations/GLU.py
caspian/activations/HardShrink.py
caspian/activations/HardSigmoid.py
caspian/activations/HardSwish.py
caspian/activations/HardTanh.py
caspian/activations/Identity.py
caspian/activations/LReLU.py
caspian/activations/PReLU.py
caspian/activations/RReLU.py
caspian/activations/ReLU.py
caspian/activations/ReLUX.py
caspian/activations/Sigmoid.py
caspian/activations/Softmax.py
caspian/activations/Softmin.py
caspian/activations/Softplus.py
caspian/activations/Softsign.py
caspian/activations/SwiGLU.py
caspian/activations/Swish.py
caspian/activations/Tanh.py
caspian/activations/__init__.py
caspian/layers/Add.py
caspian/layers/Attention.py
caspian/layers/BatchNorm.py
caspian/layers/Bilinear.py
caspian/layers/Concat.py
caspian/layers/Container.py
caspian/layers/Conv1D.py
caspian/layers/Conv1DTranspose.py
caspian/layers/Conv2D.py
caspian/layers/Conv2DTranspose.py
caspian/layers/Conv3D.py
caspian/layers/Conv3DTranspose.py
caspian/layers/ConvND.py
caspian/layers/ConvNDTranspose.py
caspian/layers/CosineSimilarity.py
caspian/layers/Dense.py
caspian/layers/Dropout.py
caspian/layers/Embedding.py
caspian/layers/GroupNorm.py
caspian/layers/InstanceNorm.py
caspian/layers/Layer.py
caspian/layers/LayerNorm.py
caspian/layers/Linear.py
caspian/layers/MatMul.py
caspian/layers/Mult.py
caspian/layers/MultiHeadAttention.py
caspian/layers/Pooling1D.py
caspian/layers/Pooling2D.py
caspian/layers/Pooling3D.py
caspian/layers/PoolingND.py
caspian/layers/PositionalEncoding.py
caspian/layers/RMSNorm.py
caspian/layers/Reshape.py
caspian/layers/Sequence.py
caspian/layers/Upsampling1D.py
caspian/layers/Upsampling2D.py
caspian/layers/Upsampling3D.py
caspian/layers/UpsamplingND.py
caspian/layers/__init__.py
caspian/losses/BinaryCrossEntropy.py
caspian/losses/CrossEntropy.py
caspian/losses/Direct.py
caspian/losses/Hinge.py
caspian/losses/Huber.py
caspian/losses/KLDivergence.py
caspian_ml-1.1.0.dist-info/LICENSE
caspian_ml-1.1.0.dist-info/METADATA
caspian_ml-1.1.0.dist-info/WHEEL
caspian_ml-1.1.0.dist-info/top_level.txt
caspian_ml-1.1.0.dist-info/RECORD
