Metadata-Version: 2.1
Name: caspian-ml
Version: 1.1.0
Summary: A deep learning library focused entirely around NumPy.
Home-page: https://github.com/Vexives/caspian
Author: Vexives
License: Apache 2.0
Keywords: machine learning,data science,deep learning,numpy
Classifier: Development Status :: 3 - Alpha
Classifier: Intended Audience :: Developers
Classifier: License :: OSI Approved :: Apache Software License
Classifier: Programming Language :: Python :: 3
Classifier: Programming Language :: Python :: 3.10
Classifier: Programming Language :: Python :: 3.11
Classifier: Topic :: Scientific/Engineering :: Mathematics
Classifier: Topic :: Software Development :: Libraries
Classifier: Operating System :: OS Independent
Requires-Python: >=3.10
License-File: LICENSE
Requires-Dist: numpy
